Workbook

Sheet Close Pack
A1: Sample Co — Monthly close pack, August 2026
A2: Every figure is a formula over the Transactions tab. Sample data only.
A3: PROFIT AND LOSS
A4: Sales (invoiced) | B4: =SUMIFS(Transactions!$E$2:$E$24,Transactions!$C$2:$C$24,"Sales",Transactions!$D$2:$D$24,"AR",Transactions!$E$2:$E$24,">0") | C4: Invoices raised in the month
A5: Cost of sales | B5: =-SUMIFS(Transactions!$E$2:$E$24,Transactions!$C$2:$C$24,"Cost of sales",Transactions!$D$2:$D$24,"AP",Transactions!$E$2:$E$24,"<0") | C5: Supplier bills for stock
A6: Gross profit | B6: =B4-B5
A7: Rent | B7: =-SUMIFS(Transactions!$E$2:$E$24,Transactions!$C$2:$C$24,"Rent",Transactions!$D$2:$D$24,"AP",Transactions!$E$2:$E$24,"<0")
A8: Salaries | B8: =-SUMIFS(Transactions!$E$2:$E$24,Transactions!$C$2:$C$24,"Salaries")
A9: Utilities | B9: =-SUMIFS(Transactions!$E$2:$E$24,Transactions!$C$2:$C$24,"Utilities")
A10: Software | B10: =-SUMIFS(Transactions!$E$2:$E$24,Transactions!$C$2:$C$24,"Software")
A11: Marketing | B11: =-SUMIFS(Transactions!$E$2:$E$24,Transactions!$C$2:$C$24,"Marketing")
A12: Insurance | B12: =-SUMIFS(Transactions!$E$2:$E$24,Transactions!$C$2:$C$24,"Insurance")
A13: Bank charges | B13: =-SUMIFS(Transactions!$E$2:$E$24,Transactions!$C$2:$C$24,"Bank charges")
A14: Total overheads | B14: =SUM(B7:B13)
A15: Net profit | B15: =B6-B14 | C15: Gross profit less overheads
A16: Gross margin | B16: =IF(B4=0,0,B6/B4)
A18: CASH AND WORKING CAPITAL
A19: Bank balance, end of month | B19: =SUMIFS(Transactions!$E$2:$E$24,Transactions!$D$2:$D$24,"Bank") | C19: Opening balance plus every cash movement
A20: Receivables outstanding | B20: =SUMIFS(Transactions!$E$2:$E$24,Transactions!$D$2:$D$24,"AR") | C20: Opening plus invoices raised, less settlements
A21: Payables outstanding | B21: =-SUMIFS(Transactions!$E$2:$E$24,Transactions!$D$2:$D$24,"AP") | C21: Bills received less payments
A22: Net working capital | B22: =B19+B20-B21
A23: Cash movement in the month | B23: =SUMIFS(Transactions!$E$2:$E$24,Transactions!$D$2:$D$24,"Bank")-SUMIFS(Transactions!$E$2:$E$24,Transactions!$B$2:$B$24,"Opening bank balance b/f") | C23: Closing bank less opening
A25: FIVE LINES IN PLAIN WORDS
A26: 1 | B26: ="Sales invoiced "&TEXT(B4,"#,##0")&" against cost of sales "&TEXT(B5,"#,##0")&" — gross margin "&TEXT(B16,"0%")&"."
A27: 2 | B27: ="Net profit for the month "&TEXT(B15,"#,##0")&" after overheads of "&TEXT(B14,"#,##0")&"."
A28: 3 | B28: ="Bank closed at "&TEXT(B19,"#,##0")&", a movement of "&TEXT(B23,"#,##0;-#,##0")&" in the month, mostly salaries and stock paid before customers paid."
A29: 4 | B29: ="Customers owe "&TEXT(B20,"#,##0")&"; every item is current — see AR Ageing."
A30: 5 | B30: ="Suppliers are owed "&TEXT(B21,"#,##0")&"; nothing is overdue at month end."

Sheet Transactions
A1: Date | B1: Description | C1: Account | D1: Type | E1: Amount | G1: Legend
A2: 2026-08-01 | B2: Opening bank balance b/f | C2: Bank | D2: Bank | E2: 18500 | G2: Blue = sample input. Type: Bank moves cash; AR is an invoice (+) or its settlement (−); AP is a bill (−) or its payment (+). Every other tab is formulas over this list.
A3: 2026-08-01 | B3: Opening receivables b/f — inv 1039 Ng & Co | C3: Opening AR | D3: AR | E3: 3100
A4: 2026-08-02 | B4: Invoice 1041 — Lim Trading | C4: Sales | D4: AR | E4: 4200
A5: 2026-08-03 | B5: Office rent August | C5: Rent | D5: AP | E5: -2500
A6: 2026-08-05 | B6: Receipt inv 1039 — Ng & Co | C6: Bank | D6: Bank | E6: 3100
A7: 2026-08-05 | B7: Settle inv 1039 | C7: Opening AR | D7: AR | E7: -3100
A8: 2026-08-07 | B8: Telco & internet | C8: Utilities | D8: Bank | E8: -180
A9: 2026-08-09 | B9: Invoice 1042 — Sun Bakery | C9: Sales | D9: AR | E9: 2650
A10: 2026-08-10 | B10: Pay rent August | C10: Bank | D10: Bank | E10: -2500
A11: 2026-08-10 | B11: Settle rent AP | C11: Rent | D11: AP | E11: 2500
A12: 2026-08-12 | B12: Software subscriptions | C12: Software | D12: Bank | E12: -260
A13: 2026-08-14 | B13: Stock purchase — Wong Supplies | C13: Cost of sales | D13: AP | E13: -3900
A14: 2026-08-15 | B14: Salaries August | C14: Salaries | D14: Bank | E14: -7800
... A24: 2026-08-30 | B24: Stock purchase — Tan Bros | C24: Cost of sales | D24: AP | E24: -2100

Sheet Bank Rec
A1: Bank reconciliation — August 2026
A3: Balance per books (Close Pack) | B3: ='Close Pack'!B19
A4: Add: cheques not yet presented | B4: 0
A5: Less: deposits not yet credited | B5: 0
A6: Balance per bank statement (type from the statement) | B6: 10365
A7: Difference (must be zero) | B7: =B3+B4-B5-B6 | C7: =IF(B7=0,"Reconciled","Investigate — items missing from books or statement")
A9: Yellow cells are typed from the bank statement. Sample statement balance shown.

Sheet AR Ageing
A1: Ref | B1: Name | C1: Date | D1: Amount | E1: Days old at 31 Aug | F1: Bucket
A2: 1042 | B2: Sun Bakery | C2: 2026-08-09 | D2: 2650 | E2: =DATE(2026,8,31)-DATEVALUE(C2) | F2: =IF(E2<=30,"Current",IF(E2<=60,"31–60",IF(E2<=90,"61–90","90+")))
A3: 1043 | B3: Harbour Clinic | C3: 2026-08-20 | D3: 9800 | E3: =DATE(2026,8,31)-DATEVALUE(C3) | F3: =IF(E3<=30,"Current",IF(E3<=60,"31–60",IF(E3<=90,"61–90","90+")))
A4: 1044 | B4: Lim Trading | C4: 2026-08-27 | D4: 3300 | E4: =DATE(2026,8,31)-DATEVALUE(C4) | F4: =IF(E4<=30,"Current",IF(E4<=60,"31–60",IF(E4<=90,"61–90","90+")))
C6: Total | D6: =SUM(D2:D4)
C7: Agrees to Close Pack? | D7: =IF(ROUND(D6-'Close Pack'!B20,0)=0,"Yes","No — check")

Sheet AP Ageing
A1: Ref | B1: Name | C1: Date | D1: Amount | E1: Days old at 31 Aug | F1: Bucket
A2: TB-88 | B2: Tan Bros | C2: 2026-08-30 | D2: 2100 | E2: =DATE(2026,8,31)-DATEVALUE(C2) | F2: =IF(E2<=30,"Current",IF(E2<=60,"31–60",IF(E2<=90,"61–90","90+")))
C4: Total | D4: =SUM(D2:D2)
C5: Agrees to Close Pack? | D5: =IF(ROUND(D4-'Close Pack'!B21,0)=0,"Yes","No — check")

Sheet Checklist
A1: Month-end step | B1: Done | C1: Note
A2: All bank and card statements downloaded
A3: Every transaction categorised
A4: Bank reconciliation difference is zero
A5: Sales invoices raised and matched to receipts
A6: Supplier bills entered and matched to payments
A7: AR and AP ageing agree to the close pack
A8: Payroll posted and agrees to payslips
A9: Prepayments and accruals reviewed
A10: Close pack sent to the client with the five lines
A12: Type Y in the yellow cells as each step is done.
