Workbook

Sheet READ ME
A1: SME Monthly Close Kit
A2: One workbook per client per month. Save a copy named e.g. ClientName-2026-08.xlsx
A4: HOW TO USE
A5: 1. Settings sheet: fill the yellow cells (client, month, opening cash).
A6: 2. Transactions sheet: enter every transaction for the month — date,
A7: description, money in OR money out, and pick a category from the dropdown.
A8: 3. That's it. P&L, Cash Summary and Client Report calculate themselves.
A9: 4. Check the Client Report page, then send it (or export it as PDF).
A11: COLOR LEGEND
A12: Yellow cells = you fill these in. Blue text = typed inputs.
A13: Black = formulas (do not overwrite). Green = pulled from another sheet.
A15: NOTES
... A18: delete it before entering a real month.

Sheet Settings
A1: CLIENT SETTINGS
A2: Client / business name | B2: Example Trading Sdn Bhd
A3: Month | B3: August 2026
A4: Opening cash balance | B4: 5000
A5: Prepared by | B5: Your name
A7: CATEGORIES | B7: Type
A8: Sales | B8: Income
A9: Other income | B9: Income
A10: Purchases / stock | B10: Expense
A11: Rent | B11: Expense
A12: Salaries & EPF/SOCSO | B12: Expense
A13: Utilities | B13: Expense
A14: Marketing | B14: Expense
A15: Transport & delivery | B15: Expense
A16: Supplies & packaging | B16: Expense
A17: Professional fees | B17: Expense
... A19: Other expenses | B19: Expense

Sheet Transactions
A1: Date | B1: Description | C1: Money in | D1: Money out | E1: Category | F1: Notes
A2: 2026-08-01 | B2: EXAMPLE — Cash sales for the day (delete this row) | C2: 850 | E2: Sales

Sheet P&L
A1: PROFIT & LOSS | B1: =Settings!B3 -> August 2026
A3: INCOME
A4: =Settings!A8 -> Sales | B4: =SUMIFS(Transactions!C2:C501,Transactions!E2:E501,A4)-SUMIFS(Transactions!D2:D501,Transactions!E2:E501,A4) -> 850
A5: =Settings!A9 -> Other income | B5: =SUMIFS(Transactions!C2:C501,Transactions!E2:E501,A5)-SUMIFS(Transactions!D2:D501,Transactions!E2:E501,A5) -> 0
A6: Total income | B6: =SUM(B4:B5) -> 850
A8: EXPENSES
A9: =Settings!A10 -> Purchases / stock | B9: =SUMIFS(Transactions!D2:D501,Transactions!E2:E501,A9)-SUMIFS(Transactions!C2:C501,Transactions!E2:E501,A9) -> 0
A10: =Settings!A11 -> Rent | B10: =SUMIFS(Transactions!D2:D501,Transactions!E2:E501,A10)-SUMIFS(Transactions!C2:C501,Transactions!E2:E501,A10) -> 0
A11: =Settings!A12 -> Salaries & EPF/SOCSO | B11: =SUMIFS(Transactions!D2:D501,Transactions!E2:E501,A11)-SUMIFS(Transactions!C2:C501,Transactions!E2:E501,A11) -> 0
A12: =Settings!A13 -> Utilities | B12: =SUMIFS(Transactions!D2:D501,Transactions!E2:E501,A12)-SUMIFS(Transactions!C2:C501,Transactions!E2:E501,A12) -> 0
A13: =Settings!A14 -> Marketing | B13: =SUMIFS(Transactions!D2:D501,Transactions!E2:E501,A13)-SUMIFS(Transactions!C2:C501,Transactions!E2:E501,A13) -> 0
A14: =Settings!A15 -> Transport & delivery | B14: =SUMIFS(Transactions!D2:D501,Transactions!E2:E501,A14)-SUMIFS(Transactions!C2:C501,Transactions!E2:E501,A14) -> 0
A15: =Settings!A16 -> Supplies & packaging | B15: =SUMIFS(Transactions!D2:D501,Transactions!E2:E501,A15)-SUMIFS(Transactions!C2:C501,Transactions!E2:E501,A15) -> 0
A16: =Settings!A17 -> Professional fees | B16: =SUMIFS(Transactions!D2:D501,Transactions!E2:E501,A16)-SUMIFS(Transactions!C2:C501,Transactions!E2:E501,A16) -> 0
A17: =Settings!A18 -> Loan repayment | B17: =SUMIFS(Transactions!D2:D501,Transactions!E2:E501,A17)-SUMIFS(Transactions!C2:C501,Transactions!E2:E501,A17) -> 0
A18: =Settings!A19 -> Other expenses | B18: =SUMIFS(Transactions!D2:D501,Transactions!E2:E501,A18)-SUMIFS(Transactions!C2:C501,Transactions!E2:E501,A18) -> 0
A19: Total expenses | B19: =SUM(B9:B18) -> 0
A21: NET PROFIT / (LOSS) | B21: =B6-B19 -> 850
A23: Uncategorized transactions | B23: =COUNTIFS(Transactions!A2:A501,"<>",Transactions!E2:E501,"") -> 0
A24: (must be 0 before you send the report)

Sheet Cash Summary
A1: CASH SUMMARY
A3: Opening balance | B3: =Settings!B4 -> 5000
A4: Total money in | B4: =SUM(Transactions!C2:C501) -> 850
A5: Total money out | B5: =SUM(Transactions!D2:D501) -> 0
A6: Closing balance | B6: =B3+B4-B5 -> 5850

Sheet Client Report
A1: MONTHLY REPORT
A2: =Settings!B2 -> Example Trading Sdn Bhd
A3: =Settings!B3 -> August 2026
A5: THE MONTH IN FOUR NUMBERS
A6: Income | B6: ='P&L'!B6 -> 850
A7: Expenses | B7: ='P&L'!B19 -> 0
A8: Net profit / (loss) | B8: ='P&L'!B21 -> 850
A9: Cash in hand at month end | B9: ='Cash Summary'!B6 -> 5850
A11: TOP 3 EXPENSES
A12: =IF(IFERROR(LARGE('P&L'!B9:B18,1),0)<=0,"-",INDEX('P&L'!A9:A18,MATCH(LARGE('P&L'!B9:B18,1),'P&L'!B9:B18,0))) -> - | B12: =IFERROR(LARGE('P&L'!B9:B18,1),0) -> 0
A13: =IF(IFERROR(LARGE('P&L'!B9:B18,2),0)<=0,"-",INDEX('P&L'!A9:A18,MATCH(LARGE('P&L'!B9:B18,2),'P&L'!B9:B18,0))) -> - | B13: =IFERROR(LARGE('P&L'!B9:B18,2),0) -> 0
A14: =IF(IFERROR(LARGE('P&L'!B9:B18,3),0)<=0,"-",INDEX('P&L'!A9:A18,MATCH(LARGE('P&L'!B9:B18,3),'P&L'!B9:B18,0))) -> - | B14: =IFERROR(LARGE('P&L'!B9:B18,3),0) -> 0
A16: NOTES FROM YOUR ACCOUNTANT
A17: Write 2-3 plain-language observations here before sending.
A19: Prepared by: | B19: =Settings!B5 -> Your name
A20: Uncategorized items check | B20: ='P&L'!B23 -> 0
