Workbook

Sheet Start Here
B2: Budget & Savings Tracker
B4: How to use this workbook (5 minutes to set up):
B5: 1. Budget sheet — type your planned monthly income and planned spend per category in the yellow cells.
B6: 2. Expense Log sheet — each time you spend money, add one row: date, category, description, amount.
B7: Pick the category from the list on the Budget sheet so totals match automatically.
B8: 3. Savings Goals sheet — list each goal, its target amount, and what you have saved so far.
B10: Everything else calculates itself: actual spend per category, money left, net for the month,
B11: your savings rate, and progress toward every goal.
B13: Legend:
B14: • Yellow cells with blue text = type here. Everything else is a formula — leave it alone.
B15: • The workbook is currency-neutral: numbers are plain amounts, so it works with any currency.
B16: • One realistic example row is pre-filled in each sheet to show the expected format. Overwrite it with
... B19: Tip: duplicate the whole file each month (File > Save a Copy) to keep a monthly archive.

Sheet Budget
B2: Monthly Budget
B4: INCOME
B5: Source | C5: Planned | D5: Actual | E5: Difference
B6: Salary | C6: 3200 | D6: 3200 | E6: =D6-C6 -> 0
B7: Side income | C7: 0 | D7: 0 | E7: =D7-C7 -> 0
B8: Other income | C8: 0 | D8: 0 | E8: =D8-C8 -> 0
B9: Total income | C9: =SUM(C6:C8) -> 3200 | D9: =SUM(D6:D8) -> 3200 | E9: =SUM(E6:E8) -> 0
B11: EXPENSES
B12: Category | C12: Planned | D12: Actual (auto) | E12: Left to spend
B13: Housing / Rent | C13: 1100 | D13: =SUMIFS('Expense Log'!$D$2:$D$500,'Expense Log'!$B$2:$B$500,B13) -> 0 | E13: =C13-D13 -> 1100
B14: Utilities | C14: 0 | D14: =SUMIFS('Expense Log'!$D$2:$D$500,'Expense Log'!$B$2:$B$500,B14) -> 0 | E14: =C14-D14 -> 0
B15: Groceries | C15: 0 | D15: =SUMIFS('Expense Log'!$D$2:$D$500,'Expense Log'!$B$2:$B$500,B15) -> 82.4 | E15: =C15-D15 -> -82.4
B16: Transport | C16: 0 | D16: =SUMIFS('Expense Log'!$D$2:$D$500,'Expense Log'!$B$2:$B$500,B16) -> 0 | E16: =C16-D16 -> 0
B17: Insurance | C17: 0 | D17: =SUMIFS('Expense Log'!$D$2:$D$500,'Expense Log'!$B$2:$B$500,B17) -> 0 | E17: =C17-D17 -> 0
B18: Health | C18: 0 | D18: =SUMIFS('Expense Log'!$D$2:$D$500,'Expense Log'!$B$2:$B$500,B18) -> 0 | E18: =C18-D18 -> 0
B19: Dining Out | C19: 0 | D19: =SUMIFS('Expense Log'!$D$2:$D$500,'Expense Log'!$B$2:$B$500,B19) -> 0 | E19: =C19-D19 -> 0
B20: Entertainment | C20: 0 | D20: =SUMIFS('Expense Log'!$D$2:$D$500,'Expense Log'!$B$2:$B$500,B20) -> 0 | E20: =C20-D20 -> 0
B21: Subscriptions | C21: 0 | D21: =SUMIFS('Expense Log'!$D$2:$D$500,'Expense Log'!$B$2:$B$500,B21) -> 0 | E21: =C21-D21 -> 0
B22: Shopping | C22: 0 | D22: =SUMIFS('Expense Log'!$D$2:$D$500,'Expense Log'!$B$2:$B$500,B22) -> 0 | E22: =C22-D22 -> 0
B23: Education | C23: 0 | D23: =SUMIFS('Expense Log'!$D$2:$D$500,'Expense Log'!$B$2:$B$500,B23) -> 0 | E23: =C23-D23 -> 0
B24: Other | C24: 0 | D24: =SUMIFS('Expense Log'!$D$2:$D$500,'Expense Log'!$B$2:$B$500,B24) -> 0 | E24: =C24-D24 -> 0
B25: Total expenses | C25: =SUM(C13:C24) -> 1100 | D25: =SUM(D13:D24) -> 82.4 | E25: =SUM(E13:E24) -> 1017.6
B27: SUMMARY
B28: Actual income | C28: =D9 -> 3200
B29: Actual expenses | C29: =D25 -> 82.4
B30: Net this month | C30: =D9-D25 -> 3117.6
B31: Savings rate | C31: =IFERROR((D9-D25)/D9,0) -> 0.97425

Sheet Expense Log
A1: Date | B1: Category | C1: Description | D1: Amount | F1: Add one row per expense. Category must match a Budget-sheet category exactly.
A2: 2026-01-03 | B2: Groceries | C2: Weekly grocery run | D2: 82.4

Sheet Savings Goals
A1: Goal | B1: Target | C1: Saved so far | D1: Remaining | E1: Progress
A2: Emergency fund | B2: 5000 | C2: 1250 | D2: =IF(B2="","",B2-C2) -> 3750 | E2: =IF(B2="","",IFERROR(C2/B2,0)) -> 0.25
D3: =IF(B3="","",B3-C3) | E3: =IF(B3="","",IFERROR(C3/B3,0))
D4: =IF(B4="","",B4-C4) | E4: =IF(B4="","",IFERROR(C4/B4,0))
D5: =IF(B5="","",B5-C5) | E5: =IF(B5="","",IFERROR(C5/B5,0))
D6: =IF(B6="","",B6-C6) | E6: =IF(B6="","",IFERROR(C6/B6,0))
D7: =IF(B7="","",B7-C7) | E7: =IF(B7="","",IFERROR(C7/B7,0))
D8: =IF(B8="","",B8-C8) | E8: =IF(B8="","",IFERROR(C8/B8,0))
D9: =IF(B9="","",B9-C9) | E9: =IF(B9="","",IFERROR(C9/B9,0))
D10: =IF(B10="","",B10-C10) | E10: =IF(B10="","",IFERROR(C10/B10,0))
D11: =IF(B11="","",B11-C11) | E11: =IF(B11="","",IFERROR(C11/B11,0))
